LICENSE
MANIFEST.in
README.md
pyproject.toml
setup.cfg
setup.py
tests/__init__.py
tests/manage.py
tests/testapp/__init__.py
tests/testapp/core/__init__.py
tests/testapp/core/tests.py
tests/testapp/core/migrations/__init__.py
tests/testapp/testapp/__init__.py
tests/testapp/testapp/asgi.py
tests/testapp/testapp/settings.py
tests/testapp/testapp/urls.py
tests/testapp/testapp/wsgi.py
wagtail_optimizer/__init__.py
wagtail_optimizer/admin.py
wagtail_optimizer/apps.py
wagtail_optimizer/forms.py
wagtail_optimizer/json.py
wagtail_optimizer/models.py
wagtail_optimizer/progress.py
wagtail_optimizer/settings.py
wagtail_optimizer/tasks.py
wagtail_optimizer/tests.py
wagtail_optimizer/views.py
wagtail_optimizer/wagtail_hooks.py
wagtail_optimizer.egg-info/PKG-INFO
wagtail_optimizer.egg-info/SOURCES.txt
wagtail_optimizer.egg-info/dependency_links.txt
wagtail_optimizer.egg-info/requires.txt
wagtail_optimizer.egg-info/top_level.txt
wagtail_optimizer/analyze/__init__.py
wagtail_optimizer/analyze/analyze.py
wagtail_optimizer/analyze/analyzers.py
wagtail_optimizer/analyze/errors.py
wagtail_optimizer/migrations/0001_initial.py
wagtail_optimizer/migrations/0002_rename_analyis_analysis.py
wagtail_optimizer/migrations/0003_alter_analysis_options_analysis_seo_score.py
wagtail_optimizer/migrations/0004_alter_analysis_seo_score.py
wagtail_optimizer/migrations/__init__.py
wagtail_optimizer/migrations/__pycache__/0001_initial.cpython-311.pyc
wagtail_optimizer/migrations/__pycache__/0002_analyis_mpw_count_analyis_p_count_analyis_spe_count_and_more.cpython-311.pyc
wagtail_optimizer/migrations/__pycache__/0002_rename_analyis_analysis.cpython-311.pyc
wagtail_optimizer/migrations/__pycache__/0003_alter_analysis_options_analysis_seo_score.cpython-311.pyc
wagtail_optimizer/migrations/__pycache__/0004_alter_analysis_seo_score.cpython-311.pyc
wagtail_optimizer/migrations/__pycache__/__init__.cpython-311.pyc
wagtail_optimizer/scraper/__init__.py
wagtail_optimizer/scraper/page.py
wagtail_optimizer/scraper/tags.py
wagtail_optimizer/static/wagtail_optimizer/css/wagtail_optimizer.css
wagtail_optimizer/static/wagtail_optimizer/js/CHARTJS_LICENSE.md
wagtail_optimizer/static/wagtail_optimizer/js/chart.min.js
